{"service": "ets", "origin": "Arau", "latest_date": "2026-07-16", "destinations": {"Alor Setar": {"baseline": [null, null, null, null, null, null, null, 1.825242718446602, 1.3142857142857143, null, 1.980952380952381, 3.0416666666666665, 2.048076923076923, null, 2.127659574468085, 2.111111111111111, null, 1.8157894736842106, null, null, 1.0, null, null, null], "baseline_730": [null, null, null, null, null, null, null, 1.825242718446602, 1.3142857142857143, null, 1.980952380952381, 3.0416666666666665, 2.048076923076923, null, 2.127659574468085, 2.111111111111111, null, 1.8157894736842106, null, null, 1.0, null, null, null], "today": [null, null, null, null, null, null, null, null, null, null, null, null, null, null, null, null, null, null, null, null, null, null, null, null]}, "Anak Bukit": {"baseline": [null, null, null, null, null, null, null, null, null, null, null, null, 1.5, null, null, 2.0, null, null, null, null, null, null, null, null], "baseline_730": [null, null, null, null, null, null, null, null, null, null, null, null, 1.5, null, null, 2.0, null, null, null, null, null, null, null, null], "today": [null, null, null, null, null, null, null, null, null, null, null, null, null, null, null, null, null, null, null, null, null, null, null, null]}, "Bagan Serai": {"baseline": [null, null, null, null, null, null, null, null, null, null, null, null, 2.042105263157895, null, null, 1.65, null, null, null, null, null, null, null, null], "baseline_730": [null, null, null, null, null, null, null, null, null, null, null, null, 2.042105263157895, null, null, 1.65, null, null, null, null, null, null, null, null], "today": [null, null, null, null, null, null, null, null, null, null, null, null, null, null, null, null, null, null, null, null, null, null, null, null]}, "Bandar Tasek Selatan": {"baseline": [null, null, null, null, null, null, null, null, 2.15, null, null, null, 2.598360655737705, null, null, null, null, null, null, null, null, null, null, null], "baseline_730": [null, null, null, null, null, null, null, null, 2.15, null, null, null, 2.598360655737705, null, null, null, null, null, null, null, null, null, null, null], "today": [null, null, null, null, null, null, null, null, null, null, null, null, null, null, null, null, null, null, null, null, null, null, null, null]}, "Batang Melaka": {"baseline": [null, null, null, null, null, null, null, null, 1.5, null, null, null, 2.8095238095238093, null, null, null, null, null, null, null, null, null, null, null], "baseline_730": [null, null, null, null, null, null, null, null, 1.5, null, null, null, 2.8095238095238093, null, null, null, null, null, null, null, null, null, null, null], "today": [null, null, null, null, null, null, null, null, null, null, null, null, null, null, null, null, null, null, null, null, null, null, null, null]}, "Batu Gajah": {"baseline": [null, null, null, null, null, null, null, 1.7311827956989247, 2.19672131147541, null, 2.2131147540983607, 2.806451612903226, 2.4864864864864864, null, null, 2.78125, null, 3.3509933774834435, null, null, 3.8333333333333335, null, null, null], "baseline_730": [null, null, null, null, null, null, null, 1.7311827956989247, 2.19672131147541, null, 2.2131147540983607, 2.806451612903226, 2.4864864864864864, null, null, 2.78125, null, 3.3509933774834435, null, null, 3.8333333333333335, null, null, null], "today": [null, null, null, null, null, null, null, null, null, null, null, null, null, null, null, null, null, null, null, null, null, null, null, null]}, "Bekok": {"baseline": [null, null, null, null, null, null, null, null, null, null, null, null, 1.5, null, null, null, null, null, null, null, null, null, null, null], "baseline_730": [null, null, null, null, null, null, null, null, null, null, null, null, 1.5, null, null, null, null, null, null, null, null, null, null, null], "today": [null, null, null, null, null, null, null, null, null, null, null, null, null, null, null, null, null, null, null, null, null, null, null, null]}, "Gemas": {"baseline": [null, null, null, null, null, null, null, null, 1.9565217391304348, null, null, null, 2.360655737704918, null, null, null, null, null, null, null, null, null, null, null], "baseline_730": [null, null, null, null, null, null, null, null, 1.9565217391304348, null, null, null, 2.360655737704918, null, null, null, null, null, null, null, null, null, null, null], "today": [null, null, null, null, null, null, null, null, null, null, null, null, null, null, null, null, null, null, null, null, null, null, null, null]}, "Gurun": {"baseline": [null, null, null, null, null, null, null, null, null, null, null, null, 1.3888888888888888, null, null, 1.6363636363636365, null, null, null, null, null, null, null, null], "baseline_730": [null, null, null, null, null, null, null, null, null, null, null, null, 1.3888888888888888, null, null, 1.6363636363636365, null, null, null, null, null, null, null, null], "today": [null, null, null, null, null, null, null, null, null, null, null, null, null, null, null, null, null, null, null, null, null, null, null, null]}, "Ipoh": {"baseline": [null, null, null, null, null, null, null, 2.7569444444444446, 4.026315789473684, null, 3.6623376623376624, 4.6, 5.24468085106383, null, 5.666666666666667, 4.175, null, 5.805714285714286, null, null, 3.6, null, null, null], "baseline_730": [null, null, null, null, null, null, null, 2.7569444444444446, 4.026315789473684, null, 3.6623376623376624, 4.6, 5.24468085106383, null, 5.666666666666667, 4.175, null, 5.805714285714286, null, null, 3.6, null, null, null], "today": [null, null, null, null, null, null, null, null, null, null, null, null, null, null, null, null, null, null, null, null, null, null, null, null]}, "JB Sentral": {"baseline": [null, null, null, null, null, null, null, null, 2.9545454545454546, null, null, null, 3.1235955056179776, null, null, null, null, null, null, null, null, null, null, null], "baseline_730": [null, null, null, null, null, null, null, null, 2.9545454545454546, null, null, null, 3.1235955056179776, null, null, null, null, null, null, null, null, null, null, null], "today": [null, null, null, null, null, null, null, null, null, null, null, null, null, null, null, null, null, null, null, null, null, null, null, null]}, "KL Sentral": {"baseline": [null, null, null, null, null, null, null, 21.408163265306122, 13.020833333333334, null, 35.56122448979592, 31.115384615384617, 12.301020408163266, null, 35.05102040816327, 22.488372093023255, null, 26.428571428571427, null, null, 27.2, null, null, null], "baseline_730": [null, null, null, null, null, null, null, 21.408163265306122, 13.020833333333334, null, 35.56122448979592, 31.115384615384617, 12.301020408163266, null, 35.05102040816327, 22.488372093023255, null, 26.428571428571427, null, null, 27.2, null, null, null], "today": [null, null, null, null, null, null, null, null, null, null, null, null, null, null, null, null, null, null, null, null, null, null, null, null]}, "Kajang": {"baseline": [null, null, null, null, null, null, null, null, null, null, null, null, 4.264150943396227, null, null, null, null, null, null, null, null, null, null, null], "baseline_730": [null, null, null, null, null, null, null, null, null, null, null, null, 4.264150943396227, null, null, null, null, null, null, null, null, null, null, null], "today": [null, null, null, null, null, null, null, null, null, null, null, null, null, null, null, null, null, null, null, null, null, null, null, null]}, "Kampar": {"baseline": [null, null, null, null, null, null, null, 1.8717948717948718, 1.8076923076923077, null, 2.6020408163265305, 2.4, 1.9565217391304348, null, null, 2.6842105263157894, null, 2.9159663865546217, null, null, 2.0, null, null, null], "baseline_730": [null, null, null, null, null, null, null, 1.8717948717948718, 1.8076923076923077, null, 2.6020408163265305, 2.4, 1.9565217391304348, null, null, 2.6842105263157894, null, 2.9159663865546217, null, null, 2.0, null, null, null], "today": [null, null, null, null, null, null, null, null, null, null, null, null, null, null, null, null, null, null, null, null, null, null, null, null]}, "Kempas Baru": {"baseline": [null, null, null, null, null, null, null, null, 2.7735849056603774, null, null, null, 2.6835443037974684, null, null, null, null, null, null, null, null, null, null, null], "baseline_730": [null, null, null, null, null, null, null, null, 2.7735849056603774, null, null, null, 2.6835443037974684, null, null, null, null, null, null, null, null, null, null, null], "today": [null, null, null, null, null, null, null, null, null, null, null, null, null, null, null, null, null, null, null, null, null, null, null, null]}, "Kluang": {"baseline": [null, null, null, null, null, null, null, null, 2.238095238095238, null, null, null, 3.0392156862745097, null, null, null, null, null, null, null, null, null, null, null], "baseline_730": [null, null, null, null, null, null, null, null, 2.238095238095238, null, null, null, 3.0392156862745097, null, null, null, null, null, null, null, null, null, null, null], "today": [null, null, null, null, null, null, null, null, null, null, null, null, null, null, null, null, null, null, null, null, null, null, null, null]}, "Kuala Kangsar": {"baseline": [null, null, null, null, null, null, null, 1.9074074074074074, 1.7407407407407407, null, 2.2083333333333335, 2.7586206896551726, 2.970149253731343, null, null, 3.193548387096774, null, 2.7007874015748032, null, null, 1.75, null, null, null], "baseline_730": [null, null, null, null, null, null, null, 1.9074074074074074, 1.7407407407407407, null, 2.2083333333333335, 2.7586206896551726, 2.970149253731343, null, null, 3.193548387096774, null, 2.7007874015748032, null, null, 1.75, null, null, null], "today": [null, null, null, null, null, null, null, null, null, null, null, null, null, null, null, null, null, null, null, null, null, null, null, null]}, "Kuala Lumpur": {"baseline": [null, null, null, null, null, null, null, 1.7195121951219512, 2.0303030303030303, null, 2.1444444444444444, 1.96, 1.8695652173913044, null, 2.4563106796116503, 2.238095238095238, null, 2.288659793814433, null, null, 2.2, null, null, null], "baseline_730": [null, null, null, null, null, null, null, 1.7195121951219512, 2.0303030303030303, null, 2.1444444444444444, 1.96, 1.8695652173913044, null, 2.4563106796116503, 2.238095238095238, null, 2.288659793814433, null, null, 2.2, null, null, null], "today": [null, null, null, null, null, null, null, null, null, null, null, null, null, null, null, null, null, null, null, null, null, null, null, null]}, "Kulai": {"baseline": [null, null, null, null, null, null, null, null, 2.962962962962963, null, null, null, 3.28125, null, null, null, null, null, null, null, null, null, null, null], "baseline_730": [null, null, null, null, null, null, null, null, 2.962962962962963, null, null, null, 3.28125, null, null, null, null, null, null, null, null, null, null, null], "today": [null, null, null, null, null, null, null, null, null, null, null, null, null, null, null, null, null, null, null, null, null, null, null, null]}, "Labis": {"baseline": [null, null, null, null, null, null, null, null, 1.7142857142857142, null, null, null, 1.391304347826087, null, null, null, null, null, null, null, null, null, null, null], "baseline_730": [null, null, null, null, null, null, null, null, 1.7142857142857142, null, null, null, 1.391304347826087, null, null, null, null, null, null, null, null, null, null, null], "today": [null, null, null, null, null, null, null, null, null, null, null, null, null, null, null, null, null, null, null, null, null, null, null, null]}, "Layang-Layang": {"baseline": [null, null, null, null, null, null, null, null, null, null, null, null, 1.0, null, null, null, null, null, null, null, null, null, null, null], "baseline_730": [null, null, null, null, null, null, null, null, null, null, null, null, 1.0, null, null, null, null, null, null, null, null, null, null, null], "today": [null, null, null, null, null, null, null, null, null, null, null, null, null, null, null, null, null, null, null, null, null, null, null, null]}, "Nibong Tebal": {"baseline": [null, null, null, null, null, null, null, null, null, null, null, null, 2.208695652173913, null, null, 2.6666666666666665, null, null, null, null, null, null, null, null], "baseline_730": [null, null, null, null, null, null, null, null, null, null, null, null, 2.208695652173913, null, null, 2.6666666666666665, null, null, null, null, null, null, null, null], "today": [null, null, null, null, null, null, null, null, null, null, null, null, null, null, null, null, null, null, null, null, null, null, null, null]}, "Padang Besar": {"baseline": [null, null, null, 1.75, null, null, null, null, null, null, null, null, 2.175, null, 3.169491525423729, null, null, 1.5454545454545454, null, null, 1.0, null, 1.2857142857142858, null], "baseline_730": [null, null, null, 1.75, null, null, null, null, null, null, null, null, 2.175, null, 3.169491525423729, null, null, 1.5454545454545454, null, null, 1.0, null, 1.2857142857142858, null], "today": [null, null, null, null, null, null, null, null, null, null, null, null, null, null, null, null, null, null, null, null, null, null, null, null]}, "Paloh": {"baseline": [null, null, null, null, null, null, null, null, null, null, null, null, 1.4, null, null, null, null, null, null, null, null, null, null, null], "baseline_730": [null, null, null, null, null, null, null, null, null, null, null, null, 1.4, null, null, null, null, null, null, null, null, null, null, null], "today": [null, null, null, null, null, null, null, null, null, null, null, null, null, null, null, null, null, null, null, null, null, null, null, null]}, "Parit Buntar": {"baseline": [null, null, null, null, null, null, null, 1.7876106194690264, 1.6363636363636365, null, 2.388888888888889, 3.25, 3.164473684210526, null, null, 3.6774193548387095, null, 3.8333333333333335, null, null, 4.222222222222222, null, null, null], "baseline_730": [null, null, null, null, null, null, null, 1.7876106194690264, 1.6363636363636365, null, 2.388888888888889, 3.25, 3.164473684210526, null, null, 3.6774193548387095, null, 3.8333333333333335, null, null, 4.222222222222222, null, null, null], "today": [null, null, null, null, null, null, null, null, null, null, null, null, null, null, null, null, null, null, null, null, null, null, null, null]}, "Pulau Sebang (Tampin)": {"baseline": [null, null, null, null, null, null, null, null, 2.8805970149253732, null, null, null, 5.135135135135135, null, null, null, null, null, null, null, null, null, null, null], "baseline_730": [null, null, null, null, null, null, null, null, 2.8805970149253732, null, null, null, 5.135135135135135, null, null, null, null, null, null, null, null, null, null, null], "today": [null, null, null, null, null, null, null, null, null, null, null, null, null, null, null, null, null, null, null, null, null, null, null, null]}, "Rawang": {"baseline": [null, null, null, null, null, null, null, null, null, null, null, null, 3.111111111111111, null, null, 2.48, null, null, null, null, null, null, null, null], "baseline_730": [null, null, null, null, null, null, null, null, null, null, null, null, 3.111111111111111, null, null, 2.48, null, null, null, null, null, null, null, null], "today": [null, null, null, null, null, null, null, null, null, null, null, null, null, null, null, null, null, null, null, null, null, null, null, null]}, "Rengam": {"baseline": [null, null, null, null, null, null, null, null, null, null, null, null, 1.1428571428571428, null, null, null, null, null, null, null, null, null, null, null], "baseline_730": [null, null, null, null, null, null, null, null, null, null, null, null, 1.1428571428571428, null, null, null, null, null, null, null, null, null, null, null], "today": [null, null, null, null, null, null, null, null, null, null, null, null, null, null, null, null, null, null, null, null, null, null, null, null]}, "Segamat": {"baseline": [null, null, null, null, null, null, null, null, 1.9333333333333333, null, null, null, 4.26, null, null, null, null, null, null, null, null, null, null, null], "baseline_730": [null, null, null, null, null, null, null, null, 1.9333333333333333, null, null, null, 4.26, null, null, null, null, null, null, null, null, null, null, null], "today": [null, null, null, null, null, null, null, null, null, null, null, null, null, null, null, null, null, null, null, null, null, null, null, null]}, "Seremban": {"baseline": [null, null, null, null, null, null, null, null, 3.4380952380952383, null, null, null, 4.625850340136054, null, null, null, null, null, null, null, null, null, null, null], "baseline_730": [null, null, null, null, null, null, null, null, 3.4380952380952383, null, null, null, 4.625850340136054, null, null, null, null, null, null, null, null, null, null, null], "today": [null, null, null, null, null, null, null, null, null, null, null, null, null, null, null, null, null, null, null, null, null, null, null, null]}, "Sungai Buloh": {"baseline": [null, null, null, null, null, null, null, 4.77710843373494, 3.8849557522123894, null, 8.230366492146597, 7.02, 4.523529411764706, null, 9.041666666666666, 6.175, null, 8.586387434554974, null, null, 8.222222222222221, null, null, null], "baseline_730": [null, null, null, null, null, null, null, 4.77710843373494, 3.8849557522123894, null, 8.230366492146597, 7.02, 4.523529411764706, null, 9.041666666666666, 6.175, null, 8.586387434554974, null, null, 8.222222222222221, null, null, null], "today": [null, null, null, null, null, null, null, null, null, null, null, null, null, null, null, null, null, null, null, null, null, null, null, null]}, "Sungai Petani": {"baseline": [null, null, null, null, null, null, null, 1.4824561403508771, 1.2857142857142858, null, 1.5913978494623655, 2.1904761904761907, 2.109090909090909, null, 2.2051282051282053, 2.727272727272727, null, 2.3577981651376145, null, null, 1.25, null, null, null], "baseline_730": [null, null, null, null, null, null, null, 1.4824561403508771, 1.2857142857142858, null, 1.5913978494623655, 2.1904761904761907, 2.109090909090909, null, 2.2051282051282053, 2.727272727272727, null, 2.3577981651376145, null, null, 1.25, null, null, null], "today": [null, null, null, null, null, null, null, null, null, null, null, null, null, null, null, null, null, null, null, null, null, null, null, null]}, "Sungai Siput": {"baseline": [null, null, null, null, null, null, null, null, null, null, null, null, 1.7857142857142858, null, null, 1.625, null, null, null, null, null, null, null, null], "baseline_730": [null, null, null, null, null, null, null, null, null, null, null, null, 1.7857142857142858, null, null, 1.625, null, null, null, null, null, null, null, null], "today": [null, null, null, null, null, null, null, null, null, null, null, null, null, null, null, null, null, null, null, null, null, null, null, null]}, "Taiping": {"baseline": [null, null, null, null, null, null, null, 2.2796610169491527, 2.1538461538461537, null, 3.164383561643836, 3.4722222222222223, 4.2, null, 4.188811188811189, 5.15, null, 3.925287356321839, null, null, 3.5, null, null, null], "baseline_730": [null, null, null, null, null, null, null, 2.2796610169491527, 2.1538461538461537, null, 3.164383561643836, 3.4722222222222223, 4.2, null, 4.188811188811189, 5.15, null, 3.925287356321839, null, null, 3.5, null, null, null], "today": [null, null, null, null, null, null, null, null, null, null, null, null, null, null, null, null, null, null, null, null, null, null, null, null]}, "Tanjong Malim": {"baseline": [null, null, null, null, null, null, null, 2.3916666666666666, 2.041095890410959, null, 3.375, 3.0, 2.7777777777777777, null, null, 3.5135135135135136, null, 3.8025477707006368, null, null, 3.3333333333333335, null, null, null], "baseline_730": [null, null, null, null, null, null, null, 2.3916666666666666, 2.041095890410959, null, 3.375, 3.0, 2.7777777777777777, null, null, 3.5135135135135136, null, 3.8025477707006368, null, null, 3.3333333333333335, null, null, null], "today": [null, null, null, null, null, null, null, null, null, null, null, null, null, null, null, null, null, null, null, null, null, null, null, null]}, "Tapah Road": {"baseline": [null, null, null, null, null, null, null, null, null, null, null, null, 3.183333333333333, null, null, 2.9, null, null, null, null, null, null, null, null], "baseline_730": [null, null, null, null, null, null, null, null, null, null, null, null, 3.183333333333333, null, null, 2.9, null, null, null, null, null, null, null, null], "today": [null, null, null, null, null, null, null, null, null, null, null, null, null, null, null, null, null, null, null, null, null, null, null, null]}, "Tasek Gelugor": {"baseline": [null, null, null, null, null, null, null, 1.380952380952381, 1.3137254901960784, null, 1.9012345679012346, 2.5714285714285716, 3.0833333333333335, null, null, 2.896551724137931, null, 3.3133333333333335, null, null, 3.0, null, null, null], "baseline_730": [null, null, null, null, null, null, null, 1.380952380952381, 1.3137254901960784, null, 1.9012345679012346, 2.5714285714285716, 3.0833333333333335, null, null, 2.896551724137931, null, 3.3133333333333335, null, null, 3.0, null, null, null], "today": [null, null, null, null, null, null, null, null, null, null, null, null, null, null, null, null, null, null, null, null, null, null, null, null]}}}