{"service": "ets", "origin": "Gurun", "latest_date": "2026-07-06", "destinations": {"Alor Setar": {"baseline": [null, null, 1.0, null, null, null, null, null, null, null, null, null, null, null, null, null, 1.263157894736842, null, null, null, null, null, null, null], "baseline_730": [null, null, 1.0, null, null, null, null, null, null, null, null, null, null, null, null, null, 1.263157894736842, null, null, null, null, null, null, null], "today": [null, null, null, null, null, null, null, null, null, null, null, null, null, null, null, null, null, null, null, null, null, null, null, null]}, "Anak Bukit": {"baseline": [null, null, null, null, null, null, null, null, null, null, null, null, null, null, null, null, 1.4, null, null, null, null, null, null, null], "baseline_730": [null, null, null, null, null, null, null, null, null, null, null, null, null, null, null, null, 1.4, null, null, null, null, null, null, null], "today": [null, null, null, null, null, null, null, null, null, null, null, null, null, null, null, null, null, null, null, null, null, null, null, null]}, "Arau": {"baseline": [null, null, null, null, null, null, null, null, null, null, null, null, null, null, null, null, 1.5666666666666667, null, null, null, null, null, null, null], "baseline_730": [null, null, null, null, null, null, null, null, null, null, null, null, null, null, null, null, 1.5666666666666667, null, null, null, null, null, null, null], "today": [null, null, null, null, null, null, null, null, null, null, null, null, null, null, null, null, null, null, null, null, null, null, null, null]}, "Bagan Serai": {"baseline": [null, null, null, null, null, null, null, null, null, null, null, null, null, 1.4285714285714286, null, 2.5714285714285716, null, null, null, null, null, null, null, null], "baseline_730": [null, null, null, null, null, null, null, null, null, null, null, null, null, 1.4285714285714286, null, 2.5714285714285716, null, null, null, null, null, null, null, null], "today": [null, null, null, null, null, null, null, null, null, null, null, null, null, null, null, null, null, null, null, null, null, null, null, null]}, "Bandar Tasek Selatan": {"baseline": [null, null, null, null, null, null, null, null, null, null, null, null, null, 1.6507936507936507, null, null, null, null, null, null, null, null, null, null], "baseline_730": [null, null, null, null, null, null, null, null, null, null, null, null, null, 1.6507936507936507, null, null, null, null, null, null, null, null, null, null], "today": [null, null, null, null, null, null, null, null, null, null, null, null, null, 1.0, null, null, null, null, null, null, null, null, null, null]}, "Batang Melaka": {"baseline": [null, null, null, null, null, null, null, null, null, null, null, null, null, 2.0, null, null, null, null, null, null, null, null, null, null], "baseline_730": [null, null, null, null, null, null, null, null, null, null, null, null, null, 2.0, null, null, null, null, null, null, null, null, null, null], "today": [null, null, null, null, null, null, null, null, null, null, null, null, null, null, null, null, null, null, null, null, null, null, null, null]}, "Batu Gajah": {"baseline": [null, null, null, null, null, null, null, null, null, null, null, null, null, 1.3695652173913044, null, 1.6363636363636365, null, null, null, null, null, null, null, null], "baseline_730": [null, null, null, null, null, null, null, null, null, null, null, null, null, 1.3695652173913044, null, 1.6363636363636365, null, null, null, null, null, null, null, null], "today": [null, null, null, null, null, null, null, null, null, null, null, null, null, null, null, null, null, null, null, null, null, null, null, null]}, "Gemas": {"baseline": [null, null, null, null, null, null, null, null, null, null, null, null, null, 1.7692307692307692, null, null, null, null, null, null, null, null, null, null], "baseline_730": [null, null, null, null, null, null, null, null, null, null, null, null, null, 1.7692307692307692, null, null, null, null, null, null, null, null, null, null], "today": [null, null, null, null, null, null, null, null, null, null, null, null, null, null, null, null, null, null, null, null, null, null, null, null]}, "Ipoh": {"baseline": [null, null, null, null, null, null, null, null, null, null, null, null, null, 2.309734513274336, null, 1.826086956521739, null, null, null, null, null, null, null, null], "baseline_730": [null, null, null, null, null, null, null, null, null, null, null, null, null, 2.309734513274336, null, 1.826086956521739, null, null, null, null, null, null, null, null], "today": [null, null, null, null, null, null, null, null, null, null, null, null, null, null, null, null, null, null, null, null, null, null, null, null]}, "JB Sentral": {"baseline": [null, null, null, null, null, null, null, null, null, null, null, null, null, 2.169811320754717, null, null, null, null, null, null, null, null, null, null], "baseline_730": [null, null, null, null, null, null, null, null, null, null, null, null, null, 2.169811320754717, null, null, null, null, null, null, null, null, null, null], "today": [null, null, null, null, null, null, null, null, null, null, null, null, null, null, null, null, null, null, null, null, null, null, null, null]}, "KL Sentral": {"baseline": [null, null, null, null, null, null, null, null, null, null, null, null, null, 4.7897727272727275, null, 5.261904761904762, null, null, null, null, null, null, null, null], "baseline_730": [null, null, null, null, null, null, null, null, null, null, null, null, null, 4.7897727272727275, null, 5.261904761904762, null, null, null, null, null, null, null, null], "today": [null, null, null, null, null, null, null, null, null, null, null, null, null, 12.0, null, null, null, null, null, null, null, null, null, null]}, "Kajang": {"baseline": [null, null, null, null, null, null, null, null, null, null, null, null, null, 2.278688524590164, null, null, null, null, null, null, null, null, null, null], "baseline_730": [null, null, null, null, null, null, null, null, null, null, null, null, null, 2.278688524590164, null, null, null, null, null, null, null, null, null, null], "today": [null, null, null, null, null, null, null, null, null, null, null, null, null, 2.0, null, null, null, null, null, null, null, null, null, null]}, "Kampar": {"baseline": [null, null, null, null, null, null, null, null, null, null, null, null, null, 1.303030303030303, null, 1.3333333333333333, null, null, null, null, null, null, null, null], "baseline_730": [null, null, null, null, null, null, null, null, null, null, null, null, null, 1.303030303030303, null, 1.3333333333333333, null, null, null, null, null, null, null, null], "today": [null, null, null, null, null, null, null, null, null, null, null, null, null, null, null, null, null, null, null, null, null, null, null, null]}, "Kempas Baru": {"baseline": [null, null, null, null, null, null, null, null, null, null, null, null, null, 2.27027027027027, null, null, null, null, null, null, null, null, null, null], "baseline_730": [null, null, null, null, null, null, null, null, null, null, null, null, null, 2.27027027027027, null, null, null, null, null, null, null, null, null, null], "today": [null, null, null, null, null, null, null, null, null, null, null, null, null, null, null, null, null, null, null, null, null, null, null, null]}, "Kluang": {"baseline": [null, null, null, null, null, null, null, null, null, null, null, null, null, 1.7333333333333334, null, null, null, null, null, null, null, null, null, null], "baseline_730": [null, null, null, null, null, null, null, null, null, null, null, null, null, 1.7333333333333334, null, null, null, null, null, null, null, null, null, null], "today": [null, null, null, null, null, null, null, null, null, null, null, null, null, null, null, null, null, null, null, null, null, null, null, null]}, "Kuala Kangsar": {"baseline": [null, null, null, null, null, null, null, null, null, null, null, null, null, 1.7796610169491525, null, 2.0, null, null, null, null, null, null, null, null], "baseline_730": [null, null, null, null, null, null, null, null, null, null, null, null, null, 1.7796610169491525, null, 2.0, null, null, null, null, null, null, null, null], "today": [null, null, null, null, null, null, null, null, null, null, null, null, null, 1.0, null, null, null, null, null, null, null, null, null, null]}, "Kuala Lumpur": {"baseline": [null, null, null, null, null, null, null, null, null, null, null, null, null, 1.3888888888888888, null, 1.3333333333333333, null, null, null, null, null, null, null, null], "baseline_730": [null, null, null, null, null, null, null, null, null, null, null, null, null, 1.3888888888888888, null, 1.3333333333333333, null, null, null, null, null, null, null, null], "today": [null, null, null, null, null, null, null, null, null, null, null, null, null, null, null, null, null, null, null, null, null, null, null, null]}, "Kulai": {"baseline": [null, null, null, null, null, null, null, null, null, null, null, null, null, 1.75, null, null, null, null, null, null, null, null, null, null], "baseline_730": [null, null, null, null, null, null, null, null, null, null, null, null, null, 1.75, null, null, null, null, null, null, null, null, null, null], "today": [null, null, null, null, null, null, null, null, null, null, null, null, null, null, null, null, null, null, null, null, null, null, null, null]}, "Labis": {"baseline": [null, null, null, null, null, null, null, null, null, null, null, null, null, 1.0, null, null, null, null, null, null, null, null, null, null], "baseline_730": [null, null, null, null, null, null, null, null, null, null, null, null, null, 1.0, null, null, null, null, null, null, null, null, null, null], "today": [null, null, null, null, null, null, null, null, null, null, null, null, null, null, null, null, null, null, null, null, null, null, null, null]}, "Nibong Tebal": {"baseline": [null, null, null, null, null, null, null, null, null, null, null, null, null, 1.4782608695652173, null, 1.125, null, null, null, null, null, null, null, null], "baseline_730": [null, null, null, null, null, null, null, null, null, null, null, null, null, 1.4782608695652173, null, 1.125, null, null, null, null, null, null, null, null], "today": [null, null, null, null, null, null, null, null, null, null, null, null, null, null, null, null, null, null, null, null, null, null, null, null]}, "Padang Besar": {"baseline": [null, null, null, null, null, null, null, null, null, null, null, null, null, null, null, null, 2.0, null, null, null, null, null, null, null], "baseline_730": [null, null, null, null, null, null, null, null, null, null, null, null, null, null, null, null, 2.0, null, null, null, null, null, null, null], "today": [null, null, null, null, null, null, null, null, null, null, null, null, null, null, null, null, null, null, null, null, null, null, null, null]}, "Paloh": {"baseline": [null, null, null, null, null, null, null, null, null, null, null, null, null, 13.0, null, null, null, null, null, null, null, null, null, null], "baseline_730": [null, null, null, null, null, null, null, null, null, null, null, null, null, 13.0, null, null, null, null, null, null, null, null, null, null], "today": [null, null, null, null, null, null, null, null, null, null, null, null, null, null, null, null, null, null, null, null, null, null, null, null]}, "Parit Buntar": {"baseline": [null, null, null, null, null, null, null, null, null, null, null, null, null, 1.8604651162790697, null, 1.6470588235294117, null, null, null, null, null, null, null, null], "baseline_730": [null, null, null, null, null, null, null, null, null, null, null, null, null, 1.8604651162790697, null, 1.6470588235294117, null, null, null, null, null, null, null, null], "today": [null, null, null, null, null, null, null, null, null, null, null, null, null, 1.0, null, null, null, null, null, null, null, null, null, null]}, "Pulau Sebang (Tampin)": {"baseline": [null, null, null, null, null, null, null, null, null, null, null, null, null, 2.1666666666666665, null, null, null, null, null, null, null, null, null, null], "baseline_730": [null, null, null, null, null, null, null, null, null, null, null, null, null, 2.1666666666666665, null, null, null, null, null, null, null, null, null, null], "today": [null, null, null, null, null, null, null, null, null, null, null, null, null, null, null, null, null, null, null, null, null, null, null, null]}, "Rawang": {"baseline": [null, null, null, null, null, null, null, null, null, null, null, null, null, 1.763157894736842, null, 1.75, null, null, null, null, null, null, null, null], "baseline_730": [null, null, null, null, null, null, null, null, null, null, null, null, null, 1.763157894736842, null, 1.75, null, null, null, null, null, null, null, null], "today": [null, null, null, null, null, null, null, null, null, null, null, null, null, null, null, null, null, null, null, null, null, null, null, null]}, "Rengam": {"baseline": [null, null, null, null, null, null, null, null, null, null, null, null, null, 2.0, null, null, null, null, null, null, null, null, null, null], "baseline_730": [null, null, null, null, null, null, null, null, null, null, null, null, null, 2.0, null, null, null, null, null, null, null, null, null, null], "today": [null, null, null, null, null, null, null, null, null, null, null, null, null, null, null, null, null, null, null, null, null, null, null, null]}, "Segamat": {"baseline": [null, null, null, null, null, null, null, null, null, null, null, null, null, 1.5185185185185186, null, null, null, null, null, null, null, null, null, null], "baseline_730": [null, null, null, null, null, null, null, null, null, null, null, null, null, 1.5185185185185186, null, null, null, null, null, null, null, null, null, null], "today": [null, null, null, null, null, null, null, null, null, null, null, null, null, null, null, null, null, null, null, null, null, null, null, null]}, "Seremban": {"baseline": [null, null, null, null, null, null, null, null, null, null, null, null, null, 2.090909090909091, null, null, null, null, null, null, null, null, null, null], "baseline_730": [null, null, null, null, null, null, null, null, null, null, null, null, null, 2.090909090909091, null, null, null, null, null, null, null, null, null, null], "today": [null, null, null, null, null, null, null, null, null, null, null, null, null, null, null, null, null, null, null, null, null, null, null, null]}, "Sungai Buloh": {"baseline": [null, null, null, null, null, null, null, null, null, null, null, null, null, 2.419642857142857, null, 2.2962962962962963, null, null, null, null, null, null, null, null], "baseline_730": [null, null, null, null, null, null, null, null, null, null, null, null, null, 2.419642857142857, null, 2.2962962962962963, null, null, null, null, null, null, null, null], "today": [null, null, null, null, null, null, null, null, null, null, null, null, null, 1.0, null, null, null, null, null, null, null, null, null, null]}, "Sungai Petani": {"baseline": [null, null, null, null, null, null, null, null, null, null, null, null, null, 1.1666666666666667, null, 1.2, null, null, null, null, null, null, null, null], "baseline_730": [null, null, null, null, null, null, null, null, null, null, null, null, null, 1.1666666666666667, null, 1.2, null, null, null, null, null, null, null, null], "today": [null, null, null, null, null, null, null, null, null, null, null, null, null, null, null, null, null, null, null, null, null, null, null, null]}, "Sungai Siput": {"baseline": [null, null, null, null, null, null, null, null, null, null, null, null, null, 1.5384615384615385, null, 1.2, null, null, null, null, null, null, null, null], "baseline_730": [null, null, null, null, null, null, null, null, null, null, null, null, null, 1.5384615384615385, null, 1.2, null, null, null, null, null, null, null, null], "today": [null, null, null, null, null, null, null, null, null, null, null, null, null, null, null, null, null, null, null, null, null, null, null, null]}, "Taiping": {"baseline": [null, null, null, null, null, null, null, null, null, null, null, null, null, 2.1475409836065573, null, 1.6956521739130435, null, null, null, null, null, null, null, null], "baseline_730": [null, null, null, null, null, null, null, null, null, null, null, null, null, 2.1475409836065573, null, 1.6956521739130435, null, null, null, null, null, null, null, null], "today": [null, null, null, null, null, null, null, null, null, null, null, null, null, 1.0, null, null, null, null, null, null, null, null, null, null]}, "Tanjong Malim": {"baseline": [null, null, null, null, null, null, null, null, null, null, null, null, null, 1.8169014084507042, null, 2.6, null, null, null, null, null, null, null, null], "baseline_730": [null, null, null, null, null, null, null, null, null, null, null, null, null, 1.8169014084507042, null, 2.6, null, null, null, null, null, null, null, null], "today": [null, null, null, null, null, null, null, null, null, null, null, null, null, null, null, null, null, null, null, null, null, null, null, null]}, "Tapah Road": {"baseline": [null, null, null, null, null, null, null, null, null, null, null, null, null, 1.34375, null, 1.2222222222222223, null, null, null, null, null, null, null, null], "baseline_730": [null, null, null, null, null, null, null, null, null, null, null, null, null, 1.34375, null, 1.2222222222222223, null, null, null, null, null, null, null, null], "today": [null, null, null, null, null, null, null, null, null, null, null, null, null, null, null, null, null, null, null, null, null, null, null, null]}, "Tasek Gelugor": {"baseline": [null, null, null, null, null, null, null, null, null, null, null, null, null, 1.2941176470588236, null, 1.0, null, null, null, null, null, null, null, null], "baseline_730": [null, null, null, null, null, null, null, null, null, null, null, null, null, 1.2941176470588236, null, 1.0, null, null, null, null, null, null, null, null], "today": [null, null, null, null, null, null, null, null, null, null, null, null, null, null, null, null, null, null, null, null, null, null, null, null]}}}