{"service": "ets", "origin": "Kampar", "latest_date": "2026-06-18", "destinations": {"Alor Setar": {"baseline": [1.8095238095238095, null, null, null, null, null, null, null, null, 2.175, null, 2.101123595505618, null, null, 2.195876288659794, 3.0, null, 2.5, 2.71875, null, null, null, null, 1.5], "baseline_730": [1.8095238095238095, null, null, null, null, null, null, null, null, 2.175, null, 2.101123595505618, null, null, 2.195876288659794, 3.0, null, 2.5, 2.71875, null, null, null, null, 1.5], "today": [null, null, null, null, null, null, null, null, null, 1.0, null, null, null, null, 2.0, null, null, 6.0, null, null, null, null, null, null]}, "Anak Bukit": {"baseline": [null, null, null, null, null, null, null, null, null, null, null, null, null, null, 1.393939393939394, null, null, null, null, null, null, null, null, 2.0], "baseline_730": [null, null, null, null, null, null, null, null, null, null, null, null, null, null, 1.393939393939394, null, null, null, null, null, null, null, null, 2.0], "today": [null, null, null, null, null, null, null, null, null, null, null, null, null, null, null, null, null, null, null, null, null, null, null, null]}, "Arau": {"baseline": [1.3928571428571428, null, null, null, null, null, null, null, null, 3.1648351648351647, null, 3.0357142857142856, null, null, 2.2758620689655173, 2.5, null, 2.3970588235294117, 2.5, null, null, null, null, 1.6363636363636365], "baseline_730": [1.3928571428571428, null, null, null, null, null, null, null, null, 3.1648351648351647, null, 3.0357142857142856, null, null, 2.2758620689655173, 2.5, null, 2.3970588235294117, 2.5, null, null, null, null, 1.6363636363636365], "today": [null, null, null, null, null, null, null, null, null, 4.0, null, null, null, null, 3.0, null, null, 2.0, null, null, null, null, null, null]}, "Bagan Serai": {"baseline": [null, null, null, null, null, null, null, null, null, null, null, null, null, null, 1.1, null, null, null, null, null, 1.3103448275862069, null, null, 1.0], "baseline_730": [null, null, null, null, null, null, null, null, null, null, null, null, null, null, 1.1, null, null, null, null, null, 1.3103448275862069, null, null, 1.0], "today": [null, null, null, null, null, null, null, null, null, null, null, null, null, null, 1.0, null, null, null, null, null, null, null, null, null]}, "Bandar Tasek Selatan": {"baseline": [null, null, null, null, null, null, null, null, null, 2.2711864406779663, 1.946808510638298, 2.111111111111111, null, null, null, 2.6263736263736264, null, null, null, null, null, null, null, null], "baseline_730": [null, null, null, null, null, null, null, null, null, 2.2711864406779663, 1.946808510638298, 2.111111111111111, null, null, null, 2.6263736263736264, null, null, null, null, null, null, null, null], "today": [null, null, null, null, null, null, null, null, null, null, 1.0, null, null, null, null, 2.0, null, null, null, null, null, null, null, null]}, "Batang Kali": {"baseline": [null, null, null, null, null, null, null, null, null, null, 1.1666666666666667, 2.0, null, 1.25, null, null, null, null, 1.0, null, null, null, null, null], "baseline_730": [null, null, null, null, null, null, null, null, null, null, 1.1666666666666667, 2.0, null, 1.25, null, null, null, null, 1.0, null, null, null, null, null], "today": [null, null, null, null, null, null, null, null, null, null, null, null, null, null, null, null, null, null, null, null, null, null, null, null]}, "Batang Melaka": {"baseline": [null, null, null, null, null, null, null, null, null, null, 1.263157894736842, 1.4166666666666667, null, null, null, 1.368421052631579, null, null, null, null, null, null, null, null], "baseline_730": [null, null, null, null, null, null, null, null, null, null, 1.263157894736842, 1.4166666666666667, null, null, null, 1.368421052631579, null, null, null, null, null, null, null, null], "today": [null, null, null, null, null, null, null, null, null, null, 1.0, null, null, null, null, null, null, null, null, null, null, null, null, null]}, "Batu Gajah": {"baseline": [1.0, null, null, null, null, null, null, null, null, 1.16, 1.0, 1.6216216216216217, 1.0, null, 1.4761904761904763, 1.0833333333333333, 1.3703703703703705, 1.6666666666666667, 1.25, null, 1.3333333333333333, 1.3043478260869565, 1.0, null], "baseline_730": [1.0, null, null, null, null, null, null, null, null, 1.16, 1.0, 1.6216216216216217, 1.0, null, 1.4761904761904763, 1.0833333333333333, 1.3703703703703705, 1.6666666666666667, 1.25, null, 1.3333333333333333, 1.3043478260869565, 1.0, null], "today": [null, null, null, null, null, null, null, null, null, 1.0, null, null, null, null, 1.0, null, null, 2.0, null, null, null, null, null, null]}, "Bekok": {"baseline": [null, null, null, null, null, null, null, null, null, null, null, null, null, null, null, 2.0, null, null, null, null, null, null, null, null], "baseline_730": [null, null, null, null, null, null, null, null, null, null, null, null, null, null, null, 2.0, null, null, null, null, null, null, null, null], "today": [null, null, null, null, null, null, null, null, null, null, null, null, null, null, null, null, null, null, null, null, null, null, null, null]}, "Bukit Mertajam": {"baseline": [null, null, null, null, null, null, null, null, null, null, 2.6693548387096775, null, null, null, null, 3.6115702479338845, 3.5816326530612246, 3.408, null, null, 3.411764705882353, null, 2.0602409638554215, null], "baseline_730": [null, null, null, null, null, null, null, null, null, null, 2.6693548387096775, null, null, null, null, 3.6115702479338845, 3.5816326530612246, 3.408, null, null, 3.411764705882353, null, 2.0602409638554215, null], "today": [null, null, null, null, null, null, null, null, null, null, null, null, null, null, null, 2.0, 1.0, 5.0, null, null, 6.0, null, null, null]}, "Butterworth": {"baseline": [null, null, null, null, null, null, null, null, null, null, 5.780645161290322, null, null, null, null, 4.756756756756757, 4.901785714285714, 3.4728682170542635, null, null, 2.8615384615384616, null, 1.7647058823529411, null], "baseline_730": [null, null, null, null, null, null, null, null, null, null, 5.780645161290322, null, null, null, null, 4.756756756756757, 4.901785714285714, 3.4728682170542635, null, null, 2.8615384615384616, null, 1.7647058823529411, null], "today": [null, null, null, null, null, null, null, null, null, null, 1.0, null, null, null, null, 4.0, 1.0, 11.0, null, null, null, null, 3.0, null]}, "Gemas": {"baseline": [null, null, null, null, null, null, null, null, null, 2.25, 1.5365853658536586, 1.6, null, null, null, 1.55, null, null, null, null, null, null, null, null], "baseline_730": [null, null, null, null, null, null, null, null, null, 2.25, 1.5365853658536586, 1.6, null, null, null, 1.55, null, null, null, null, null, null, null, null], "today": [null, null, null, null, null, null, null, null, null, null, null, null, null, null, null, null, null, null, null, null, null, null, null, null]}, "Gurun": {"baseline": [null, null, null, null, null, null, null, null, null, null, null, null, null, null, 1.125, null, null, null, null, null, null, null, null, 2.0], "baseline_730": [null, null, null, null, null, null, null, null, null, null, null, null, null, null, 1.125, null, null, null, null, null, null, null, null, 2.0], "today": [null, null, null, null, null, null, null, null, null, null, null, null, null, null, 2.0, null, null, null, null, null, null, null, null, null]}, "Ipoh": {"baseline": [1.6382978723404256, null, null, null, null, null, null, null, null, 3.543307086614173, 1.9411764705882353, 9.9079754601227, 9.583333333333334, null, 2.5736434108527133, 2.2658227848101267, 5.474747474747475, 8.609756097560975, 2.0526315789473686, null, 1.4179104477611941, 3.4651162790697674, 1.2105263157894737, 1.4], "baseline_730": [1.6382978723404256, null, null, null, null, null, null, null, null, 3.543307086614173, 1.9411764705882353, 9.9079754601227, 9.583333333333334, null, 2.5736434108527133, 2.2658227848101267, 5.474747474747475, 8.609756097560975, 2.0526315789473686, null, 1.4179104477611941, 3.4651162790697674, 1.2105263157894737, 1.4], "today": [null, null, null, null, null, null, null, null, null, 3.0, 1.0, 10.0, null, null, 1.0, null, 5.0, 20.0, null, null, null, 6.0, 1.0, null]}, "JB Sentral": {"baseline": [null, null, null, null, null, null, null, null, null, 5.700854700854701, null, 5.647058823529412, null, null, null, 3.5254237288135593, null, null, null, null, null, null, null, null], "baseline_730": [null, null, null, null, null, null, null, null, null, 5.700854700854701, null, 5.647058823529412, null, null, null, 3.5254237288135593, null, null, null, null, null, null, null, null], "today": [null, null, null, null, null, null, null, null, null, 5.0, null, 10.0, null, null, null, 3.0, null, null, null, null, null, null, null, null]}, "KL Sentral": {"baseline": [null, null, null, null, null, 18.198795180722893, null, 4.810126582278481, 3.993333333333333, 25.36144578313253, 7.115853658536586, 4.404494382022472, 26.867469879518072, 6.386075949367089, 5.163265306122449, 2.1652173913043478, null, null, 11.07361963190184, 21.97590361445783, 7.012195121951219, null, null, 2.6666666666666665], "baseline_730": [null, null, null, null, null, 18.198795180722893, null, 4.810126582278481, 3.993333333333333, 25.36144578313253, 7.115853658536586, 4.404494382022472, 26.867469879518072, 6.386075949367089, 5.163265306122449, 2.1652173913043478, null, null, 11.07361963190184, 21.97590361445783, 7.012195121951219, null, null, 2.6666666666666665], "today": [null, null, null, null, null, 17.0, null, 4.0, 3.0, 13.0, 1.0, null, 19.0, 3.0, null, 1.0, null, null, 8.0, 26.0, 6.0, null, null, null]}, "Kajang": {"baseline": [null, null, null, null, null, null, null, null, null, null, 2.150943396226415, null, null, null, null, 1.7377049180327868, null, null, null, null, null, null, null, null], "baseline_730": [null, null, null, null, null, null, null, null, null, null, 2.150943396226415, null, null, null, null, 1.7377049180327868, null, null, null, null, null, null, null, null], "today": [null, null, null, null, null, null, null, null, null, null, 2.0, null, null, null, null, null, null, null, null, null, null, null, null, null]}, "Kempas Baru": {"baseline": [null, null, null, null, null, null, null, null, null, 2.0714285714285716, null, 2.3863636363636362, null, null, null, 1.9056603773584906, null, null, null, null, null, null, null, null], "baseline_730": [null, null, null, null, null, null, null, null, null, 2.0714285714285716, null, 2.3863636363636362, null, null, null, 1.9056603773584906, null, null, null, null, null, null, null, null], "today": [null, null, null, null, null, null, null, null, null, 1.0, null, null, null, null, null, null, null, null, null, null, null, null, null, null]}, "Kepong Sentral": {"baseline": [null, null, null, null, null, 1.8764044943820224, null, null, null, 2.2452830188679247, 1.5833333333333333, 3.2, 2.664233576642336, 2.6, null, null, null, null, 2.3846153846153846, 2.815068493150685, null, null, null, null], "baseline_730": [null, null, null, null, null, 1.8764044943820224, null, null, null, 2.2452830188679247, 1.5833333333333333, 3.2, 2.664233576642336, 2.6, null, null, null, null, 2.3846153846153846, 2.815068493150685, null, null, null, null], "today": [null, null, null, null, null, null, null, null, null, null, null, null, 2.0, null, null, null, null, null, null, 10.0, null, null, null, null]}, "Klang": {"baseline": [null, null, null, null, null, null, null, null, null, null, null, null, null, null, null, null, null, null, 1.3333333333333333, null, null, null, null, null], "baseline_730": [null, null, null, null, null, null, null, null, null, null, null, null, null, null, null, null, null, null, 1.3333333333333333, null, null, null, null, null], "today": [null, null, null, null, null, null, null, null, null, null, null, null, null, null, null, null, null, null, null, null, null, null, null, null]}, "Kluang": {"baseline": [null, null, null, null, null, null, null, null, null, 1.564102564102564, null, 1.6774193548387097, null, null, null, 1.8709677419354838, null, null, null, null, null, null, null, null], "baseline_730": [null, null, null, null, null, null, null, null, null, 1.564102564102564, null, 1.6774193548387097, null, null, null, 1.8709677419354838, null, null, null, null, null, null, null, null], "today": [null, null, null, null, null, null, null, null, null, null, null, null, null, null, null, null, null, null, null, null, null, null, null, null]}, "Kuala Kangsar": {"baseline": [1.0, null, null, null, null, null, null, null, null, 1.2058823529411764, 1.5909090909090908, 1.1578947368421053, null, null, 1.1379310344827587, 1.2553191489361701, 1.3181818181818181, 1.2926829268292683, 1.2, null, 1.3870967741935485, null, 1.4375, 1.0], "baseline_730": [1.0, null, null, null, null, null, null, null, null, 1.2058823529411764, 1.5909090909090908, 1.1578947368421053, null, null, 1.1379310344827587, 1.2553191489361701, 1.3181818181818181, 1.2926829268292683, 1.2, null, 1.3870967741935485, null, 1.4375, 1.0], "today": [null, null, null, null, null, null, null, null, null, null, null, null, null, null, null, null, null, 2.0, null, null, null, null, 1.0, null]}, "Kuala Kubu Bharu": {"baseline": [null, null, null, null, null, null, null, null, null, null, null, null, null, 2.0, null, null, null, null, null, null, null, null, null, null], "baseline_730": [null, null, null, null, null, null, null, null, null, null, null, null, null, 2.0, null, null, null, null, null, null, null, null, null, null], "today": [null, null, null, null, null, null, null, null, null, null, null, null, null, null, null, null, null, null, null, null, null, null, null, null]}, "Kuala Lumpur": {"baseline": [null, null, null, null, null, 1.6779661016949152, null, 1.1, 1.368421052631579, 1.394736842105263, 1.3333333333333333, 1.5, 1.6470588235294117, 1.0588235294117647, 1.3333333333333333, 1.125, null, null, 1.2162162162162162, 1.6666666666666667, 1.391304347826087, null, null, 1.0], "baseline_730": [null, null, null, null, null, 1.6779661016949152, null, 1.1, 1.368421052631579, 1.394736842105263, 1.3333333333333333, 1.5, 1.6470588235294117, 1.0588235294117647, 1.3333333333333333, 1.125, null, null, 1.2162162162162162, 1.6666666666666667, 1.391304347826087, null, null, 1.0], "today": [null, null, null, null, null, null, null, null, null, null, null, null, null, null, null, null, null, null, null, 1.0, null, null, null, null]}, "Kulai": {"baseline": [null, null, null, null, null, null, null, null, null, 2.236842105263158, null, 2.024390243902439, null, null, null, 1.9838709677419355, null, null, null, null, null, null, null, null], "baseline_730": [null, null, null, null, null, null, null, null, null, 2.236842105263158, null, 2.024390243902439, null, null, null, 1.9838709677419355, null, null, null, null, null, null, null, null], "today": [null, null, null, null, null, null, null, null, null, null, null, null, null, null, null, 3.0, null, null, null, null, null, null, null, null]}, "Labis": {"baseline": [null, null, null, null, null, null, null, null, null, 1.125, null, 1.3333333333333333, null, null, null, 1.0, null, null, null, null, null, null, null, null], "baseline_730": [null, null, null, null, null, null, null, null, null, 1.125, null, 1.3333333333333333, null, null, null, 1.0, null, null, null, null, null, null, null, null], "today": [null, null, null, null, null, null, null, null, null, null, null, null, null, null, null, null, null, null, null, null, null, null, null, null]}, "Layang-Layang": {"baseline": [null, null, null, null, null, null, null, null, null, null, null, null, null, null, null, 1.3333333333333333, null, null, null, null, null, null, null, null], "baseline_730": [null, null, null, null, null, null, null, null, null, null, null, null, null, null, null, 1.3333333333333333, null, null, null, null, null, null, null, null], "today": [null, null, null, null, null, null, null, null, null, null, null, null, null, null, null, null, null, null, null, null, null, null, null, null]}, "Nibong Tebal": {"baseline": [null, null, null, null, null, null, null, null, null, null, null, null, null, null, 1.4583333333333333, null, null, null, null, null, 2.0632911392405062, null, null, 1.0], "baseline_730": [null, null, null, null, null, null, null, null, null, null, null, null, null, null, 1.4583333333333333, null, null, null, null, null, 2.0632911392405062, null, null, 1.0], "today": [null, null, null, null, null, null, null, null, null, null, null, null, null, null, 2.0, null, null, null, null, null, 1.0, null, null, null]}, "Padang Besar": {"baseline": [3.085714285714286, null, null, null, null, null, null, null, null, 5.381443298969073, null, 2.22, null, null, 1.4545454545454546, 2.5, null, 1.1538461538461537, 1.4285714285714286, null, null, null, null, 1.3333333333333333], "baseline_730": [3.085714285714286, null, null, null, null, null, null, null, null, 5.381443298969073, null, 2.22, null, null, 1.4545454545454546, 2.5, null, 1.1538461538461537, 1.4285714285714286, null, null, null, null, 1.3333333333333333], "today": [null, null, null, null, null, null, null, null, null, 2.0, null, null, null, null, null, null, null, null, null, null, null, null, null, null]}, "Paloh": {"baseline": [null, null, null, null, null, null, null, null, null, null, null, null, null, null, null, 1.5, null, null, null, null, null, null, null, null], "baseline_730": [null, null, null, null, null, null, null, null, null, null, null, null, null, null, null, 1.5, null, null, null, null, null, null, null, null], "today": [null, null, null, null, null, null, null, null, null, null, null, null, null, null, null, null, null, null, null, null, null, null, null, null]}, "Parit Buntar": {"baseline": [1.0, null, null, null, null, null, null, null, null, 1.4444444444444444, 1.1578947368421053, 1.394736842105263, null, null, 1.425, 1.6290322580645162, 1.9090909090909092, 1.7777777777777777, 1.5, null, 1.296875, null, 1.08, 1.25], "baseline_730": [1.0, null, null, null, null, null, null, null, null, 1.4444444444444444, 1.1578947368421053, 1.394736842105263, null, null, 1.425, 1.6290322580645162, 1.9090909090909092, 1.7777777777777777, 1.5, null, 1.296875, null, 1.08, 1.25], "today": [null, null, null, null, null, null, null, null, null, 1.0, null, null, null, null, null, null, 1.0, 4.0, null, null, 1.0, null, 1.0, null]}, "Pulau Sebang (Tampin)": {"baseline": [null, null, null, null, null, null, null, null, null, 1.4193548387096775, 2.752577319587629, 1.5, null, null, null, 2.0, null, null, null, null, null, null, null, null], "baseline_730": [null, null, null, null, null, null, null, null, null, 1.4193548387096775, 2.752577319587629, 1.5, null, null, null, 2.0, null, null, null, null, null, null, null, null], "today": [null, null, null, null, null, null, null, null, null, null, 2.0, null, null, null, null, null, null, null, null, null, null, null, null, null]}, "Rawang": {"baseline": [null, null, null, null, null, 1.4259259259259258, null, null, null, 1.631578947368421, 1.4545454545454546, 2.6666666666666665, 1.7802197802197801, 2.25, null, 1.5238095238095237, null, null, 2.5357142857142856, 2.2242990654205608, null, null, null, null], "baseline_730": [null, null, null, null, null, 1.4259259259259258, null, null, null, 1.631578947368421, 1.4545454545454546, 2.6666666666666665, 1.7802197802197801, 2.25, null, 1.5238095238095237, null, null, 2.5357142857142856, 2.2242990654205608, null, null, null, null], "today": [null, null, null, null, null, null, null, null, null, null, null, null, null, null, null, null, null, null, null, 3.0, null, null, null, null]}, "Rengam": {"baseline": [null, null, null, null, null, null, null, null, null, null, null, null, null, null, null, 1.0, null, null, null, null, null, null, null, null], "baseline_730": [null, null, null, null, null, null, null, null, null, null, null, null, null, null, null, 1.0, null, null, null, null, null, null, null, null], "today": [null, null, null, null, null, null, null, null, null, null, null, null, null, null, null, null, null, null, null, null, null, null, null, null]}, "Segamat": {"baseline": [null, null, null, null, null, null, null, null, null, 1.2941176470588236, 2.1451612903225805, 1.5238095238095237, null, null, null, 1.5625, null, null, null, null, null, null, null, null], "baseline_730": [null, null, null, null, null, null, null, null, null, 1.2941176470588236, 2.1451612903225805, 1.5238095238095237, null, null, null, 1.5625, null, null, null, null, null, null, null, null], "today": [null, null, null, null, null, null, null, null, null, null, null, null, null, null, null, null, null, null, null, null, null, null, null, null]}, "Seremban": {"baseline": [null, null, null, null, null, null, null, null, null, 1.7758620689655173, 2.267857142857143, 1.7551020408163265, null, null, null, 1.8181818181818181, null, null, null, null, null, null, null, null], "baseline_730": [null, null, null, null, null, null, null, null, null, 1.7758620689655173, 2.267857142857143, 1.7551020408163265, null, null, null, 1.8181818181818181, null, null, null, null, null, null, null, null], "today": [null, null, null, null, null, null, null, null, null, 2.0, null, null, null, null, null, null, null, null, null, null, null, null, null, null]}, "Shah Alam": {"baseline": [null, null, null, null, null, null, null, null, null, null, null, null, null, null, null, null, null, null, 1.0, null, null, null, null, null], "baseline_730": [null, null, null, null, null, null, null, null, null, null, null, null, null, null, null, null, null, null, 1.0, null, null, null, null, null], "today": [null, null, null, null, null, null, null, null, null, null, null, null, null, null, null, null, null, null, null, null, null, null, null, null]}, "Slim River": {"baseline": [null, null, null, null, null, 1.3076923076923077, null, null, null, 1.173913043478261, 1.0, 1.0, 1.52, 1.0, null, null, null, null, 1.4166666666666667, 1.2222222222222223, null, null, null, null], "baseline_730": [null, null, null, null, null, 1.3076923076923077, null, null, null, 1.173913043478261, 1.0, 1.0, 1.52, 1.0, null, null, null, null, 1.4166666666666667, 1.2222222222222223, null, null, null, null], "today": [null, null, null, null, null, null, null, null, null, null, null, null, null, null, null, null, null, null, null, 1.0, null, null, null, null]}, "Subang Jaya": {"baseline": [null, null, null, null, null, null, null, null, null, null, null, null, null, null, null, null, null, null, 1.0, null, null, null, null, null], "baseline_730": [null, null, null, null, null, null, null, null, null, null, null, null, null, null, null, null, null, null, 1.0, null, null, null, null, null], "today": [null, null, null, null, null, null, null, null, null, null, null, null, null, null, null, null, null, null, null, null, null, null, null, null]}, "Sungai Buloh": {"baseline": [null, null, null, null, null, 2.5664335664335662, null, 1.3508771929824561, 1.5689655172413792, 2.484848484848485, 1.9268292682926829, 1.5588235294117647, 3.0942028985507246, 1.8571428571428572, 1.7692307692307692, 1.368421052631579, null, null, 2.939655172413793, 4.066225165562914, 2.0096153846153846, null, null, null], "baseline_730": [null, null, null, null, null, 2.5664335664335662, null, 1.3508771929824561, 1.5689655172413792, 2.484848484848485, 1.9268292682926829, 1.5588235294117647, 3.0942028985507246, 1.8571428571428572, 1.7692307692307692, 1.368421052631579, null, null, 2.939655172413793, 4.066225165562914, 2.0096153846153846, null, null, null], "today": [null, null, null, null, null, 5.0, null, null, 1.0, null, null, null, 1.0, null, null, null, null, null, 3.0, 3.0, 1.0, null, null, null]}, "Sungai Petani": {"baseline": [1.3658536585365855, null, null, null, null, null, null, null, null, 1.9397590361445782, null, 1.8969072164948453, null, null, 2.011764705882353, 2.4444444444444446, null, 2.651685393258427, 2.2093023255813953, null, null, null, null, 1.2307692307692308], "baseline_730": [1.3658536585365855, null, null, null, null, null, null, null, null, 1.9397590361445782, null, 1.8969072164948453, null, null, 2.011764705882353, 2.4444444444444446, null, 2.651685393258427, 2.2093023255813953, null, null, null, null, 1.2307692307692308], "today": [null, null, null, null, null, null, null, null, null, null, null, 2.0, null, null, null, null, null, 4.0, null, null, null, null, null, null]}, "Sungai Siput": {"baseline": [null, null, null, null, null, null, null, null, null, null, null, null, null, null, 1.4193548387096775, null, null, null, null, null, 1.275, null, null, 1.0], "baseline_730": [null, null, null, null, null, null, null, null, null, null, null, null, null, null, 1.4193548387096775, null, null, null, null, null, 1.275, null, null, 1.0], "today": [null, null, null, null, null, null, null, null, null, null, null, null, null, null, 1.0, null, null, null, null, null, 2.0, null, null, null]}, "Sungkai": {"baseline": [null, null, null, null, null, 1.5, null, null, null, 1.0625, null, 1.0, 1.1818181818181819, 1.0, null, null, null, null, 1.0, 1.3157894736842106, null, null, null, null], "baseline_730": [null, null, null, null, null, 1.5, null, null, null, 1.0625, null, 1.0, 1.1818181818181819, 1.0, null, null, null, null, 1.0, 1.3157894736842106, null, null, null, null], "today": [null, null, null, null, null, null, null, null, null, null, null, null, null, null, null, null, null, null, null, null, null, null, null, null]}, "Taiping": {"baseline": [1.2941176470588236, null, null, null, null, null, null, null, null, 1.821917808219178, 1.7727272727272727, 1.6206896551724137, null, null, 1.7375, 2.450980392156863, 2.3544303797468356, 2.9444444444444446, 2.1363636363636362, null, 2.111111111111111, null, 1.5681818181818181, 1.4], "baseline_730": [1.2941176470588236, null, null, null, null, null, null, null, null, 1.821917808219178, 1.7727272727272727, 1.6206896551724137, null, null, 1.7375, 2.450980392156863, 2.3544303797468356, 2.9444444444444446, 2.1363636363636362, null, 2.111111111111111, null, 1.5681818181818181, 1.4], "today": [null, null, null, null, null, null, null, null, null, 3.0, 1.0, null, null, null, 1.0, 1.0, null, 5.0, null, null, 2.0, null, null, null]}, "Tanjong Malim": {"baseline": [null, null, null, null, null, 1.3725490196078431, null, 1.3076923076923077, 1.125, 1.5384615384615385, 1.32, 1.3461538461538463, 1.7457627118644068, 1.6590909090909092, 1.375, 1.3414634146341464, null, null, 1.8088235294117647, 1.8271604938271604, 1.7105263157894737, null, null, 1.5], "baseline_730": [null, null, null, null, null, 1.3725490196078431, null, 1.3076923076923077, 1.125, 1.5384615384615385, 1.32, 1.3461538461538463, 1.7457627118644068, 1.6590909090909092, 1.375, 1.3414634146341464, null, null, 1.8088235294117647, 1.8271604938271604, 1.7105263157894737, null, null, 1.5], "today": [null, null, null, null, null, null, null, null, null, null, null, null, 4.0, null, null, null, null, null, null, 1.0, 1.0, null, null, null]}, "Tapah Road": {"baseline": [null, null, null, null, null, 1.0, null, null, null, 1.1666666666666667, 1.0, 1.0, 1.3636363636363635, 1.3333333333333333, null, 1.2857142857142858, null, null, 1.3, 2.074074074074074, null, null, null, null], "baseline_730": [null, null, null, null, null, 1.0, null, null, null, 1.1666666666666667, 1.0, 1.0, 1.3636363636363635, 1.3333333333333333, null, 1.2857142857142858, null, null, 1.3, 2.074074074074074, null, null, null, null], "today": [null, null, null, null, null, null, null, null, null, null, null, null, null, null, null, 1.0, null, null, null, 2.0, null, null, null, null]}, "Tasek Gelugor": {"baseline": [1.1666666666666667, null, null, null, null, null, null, null, null, 1.4166666666666667, null, 1.2962962962962963, null, null, 1.375, 2.2, null, 1.6521739130434783, 1.4444444444444444, null, null, null, null, 1.0], "baseline_730": [1.1666666666666667, null, null, null, null, null, null, null, null, 1.4166666666666667, null, 1.2962962962962963, null, null, 1.375, 2.2, null, 1.6521739130434783, 1.4444444444444444, null, null, null, null, 1.0], "today": [null, null, null, null, null, null, null, null, null, null, null, null, null, null, 1.0, null, null, 1.0, null, null, null, null, null, null]}}}